example/__init__.py
example/example_client.py
example/example_config.py
example/example_server.py
mqtasks/__init__.py
mqtasks/body.py
mqtasks/channel.py
mqtasks/client.py
mqtasks/context.py
mqtasks/headers.py
mqtasks/message.py
mqtasks/message_id_factory.py
mqtasks/mqtask_strategy.py
mqtasks/mqtasks.py
mqtasks/mqtasks_message_context.py
mqtasks/register.py
mqtasks/response_status.py
mqtasks/response_types.py
mqtasks/utils.py
mqtasks-0.2.5.dist-info/licenses/LICENSE
mqtasks-0.2.5.dist-info/METADATA
mqtasks-0.2.5.dist-info/WHEEL
mqtasks-0.2.5.dist-info/top_level.txt
mqtasks-0.2.5.dist-info/RECORD
