Metadata-Version: 2.4
Name: mqtasks
Version: 0.2.5
Summary: This module provides a framework for handling and processing asynchronous tasks through message queues.
Home-page: https://github.com/NeuralInnovations/mqtasks-python
License: MIT
Project-URL: Bug Tracker, https://github.com/NeuralInnovations/mqtasks-python/issues
Project-URL: Documentation, https://github.com/NeuralInnovations/mqtasks-python/blob/main/README.md
Project-URL: Source Code, https://github.com/NeuralInnovations/mqtasks-python
License-File: LICENSE
Requires-Dist: asyncio==3.4.*,>=3.4.3
Requires-Dist: aio_pika==9.4.*,>=9.4.3
Requires-Dist: pydantic==2.12.*,>=2.12.4
Requires-Dist: aiormq==6.8.*,>=6.8.1
Dynamic: license-file
